[
   {
      "set":1,
      "text":"it's time to ~",
      "mean":"~ 할 시간이다",
      "image":1,
      "sound":1
   },
   {
      "set":1,
      "text":"get out of",
      "mean":"벗어나다",
      "image":2,
      "sound":2
   },
   {
      "set":1,
      "text":"refreshed",
      "mean":"상쾌한",
      "image":3,
      "sound":3
   },
   {
      "set":1,
      "text":"ready",
      "mean":"준비된",
      "image":4,
      "sound":4
   },
   {
      "set":2,
      "text":"At the breakfast table",
      "mean":"아침상에서",
      "image":5,
      "sound":5
   },
   {
      "set":2,
      "text":"prefer",
      "mean":"좋아해",
      "image":6,
      "sound":6
   },
   {
      "set":2,
      "text":"make coffee",
      "mean":"커피 만들기를",
      "image":7,
      "sound":7
   }
]